.gitignore
CHANGES.txt
CONTRIBUTORS.txt
MANIFEST.in
README.rst
bootstrap.py
buildout.cfg
setup.py
collective/__init__.py
collective.js.enquire.egg-info/PKG-INFO
collective.js.enquire.egg-info/SOURCES.txt
collective.js.enquire.egg-info/dependency_links.txt
collective.js.enquire.egg-info/entry_points.txt
collective.js.enquire.egg-info/namespace_packages.txt
collective.js.enquire.egg-info/not-zip-safe
collective.js.enquire.egg-info/requires.txt
collective.js.enquire.egg-info/top_level.txt
collective/js/__init__.py
collective/js/enquire/__init__.py
collective/js/enquire/configure.zcml
collective/js/enquire/enquire.min.js
collective/js/enquire/interfaces.py
collective/js/enquire/upgrades.py
collective/js/enquire/upgrades.zcml
collective/js/enquire/example/__init__.py
collective/js/enquire/example/configure.zcml
collective/js/enquire/example/enquire.pt
collective/js/enquire/profiles/default/jsregistry.xml
collective/js/enquire/profiles/default/metadata.xml
docs/HISTORY.txt
docs/LICENSE.txt